setup.py
lzytools/__init__.py
lzytools.egg-info/PKG-INFO
lzytools.egg-info/SOURCES.txt
lzytools.egg-info/dependency_links.txt
lzytools.egg-info/top_level.txt
lzytools/common/__init__.py
lzytools/common/_container.py
lzytools/common/_function.py
lzytools/common/_network.py
lzytools/common/_program.py
lzytools/common/_socket.py
lzytools/common/_str.py
lzytools/file/__init__.py
lzytools/file/_filename.py
lzytools/file/_filepath.py
lzytools/file/_hash.py
lzytools/file/_info.py
lzytools/file/_operation.py
lzytools/file/_properties.py
lzytools/time/__init__.py
lzytools/time/_time.py