Metadata-Version: 2.4
Name: lzytools
Version: 0.1.2
Summary: Python自用包
Home-page: https://github.com/PPJUST/lzytools
Author: PPJUST
Requires-Python: >=3
Dynamic: author
Dynamic: description
Dynamic: description-content-type
Dynamic: home-page
Dynamic: requires-python
Dynamic: summary
